[
  {
    "source": "^User Clicks on Sign in Button$",
    "steps": [
      {
        "name": "User Clicks on Sign in Button",
        "aggregatedDurations": {
          "average": 1.924244731,
          "median": 1.924244731
        },
        "durations": [
          {
            "duration": 1.924244731,
            "location": "features/Login.feature:11"
          }
        ]
      }
    ]
  },
  {
    "source": "^User is navigated to the Chat Page of the Application$",
    "steps": [
      {
        "name": "User is navigated to the Chat Page of the Application",
        "aggregatedDurations": {
          "average": 3.170566377,
          "median": 3.170566377
        },
        "durations": [
          {
            "duration": 3.170566377,
            "location": "features/Login.feature:19"
          }
        ]
      }
    ]
  },
  {
    "source": "^User Clicks on Next Button$",
    "steps": [
      {
        "name": "User Clicks on Next Button",
        "aggregatedDurations": {
          "average": 4.04611497,
          "median": 4.04611497
        },
        "durations": [
          {
            "duration": 4.04611497,
            "location": "features/Login.feature:9"
          }
        ]
      }
    ]
  },
  {
    "source": "^User Clicks on the Chat Icon at Bottom of Home Page$",
    "steps": [
      {
        "name": "User Clicks on the Chat Icon at Bottom of Home Page",
        "aggregatedDurations": {
          "average": 3.078870351,
          "median": 3.078870351
        },
        "durations": [
          {
            "duration": 3.078870351,
            "location": "features/Login.feature:18"
          }
        ]
      }
    ]
  },
  {
    "source": "^User should be able to see Splash Screen$",
    "steps": [
      {
        "name": "User should be able to see Splash Screen",
        "aggregatedDurations": {
          "average": 0.000061838,
          "median": 0.000061838
        },
        "durations": [
          {
            "duration": 0.000061838,
            "location": "features/Login.feature:6"
          }
        ]
      }
    ]
  },
  {
    "source": "^User Enters Password$",
    "steps": [
      {
        "name": "User Enters Password",
        "aggregatedDurations": {
          "average": 8.795166841,
          "median": 8.795166841
        },
        "durations": [
          {
            "duration": 8.795166841,
            "location": "features/Login.feature:10"
          }
        ]
      }
    ]
  },
  {
    "source": "^User Enters Username$",
    "steps": [
      {
        "name": "User Enters Username",
        "aggregatedDurations": {
          "average": 4.394418953,
          "median": 4.394418953
        },
        "durations": [
          {
            "duration": 4.394418953,
            "location": "features/Login.feature:8"
          }
        ]
      }
    ]
  },
  {
    "source": "^User is navigated to Azure Directory for Login$",
    "steps": [
      {
        "name": "User is navigated to Azure Directory for Login",
        "aggregatedDurations": {
          "average": 5.880873472,
          "median": 5.880873472
        },
        "durations": [
          {
            "duration": 5.880873472,
            "location": "features/Login.feature:7"
          }
        ]
      }
    ]
  },
  {
    "source": "^PruBuddy sends Response Text \"(.*?)\"$",
    "steps": [
      {
        "name": "PruBuddy sends Response Text \"Hello, I am PRUBuddy,  your virtual assistant\"",
        "aggregatedDurations": {
          "average": 3.027064953,
          "median": 3.027064953
        },
        "durations": [
          {
            "duration": 3.027064953,
            "location": "features/Login.feature:24"
          }
        ]
      },
      {
        "name": "PruBuddy sends Response Text \"May I know what is your job level?\"",
        "aggregatedDurations": {
          "average": 3.257303613,
          "median": 3.257303613
        },
        "durations": [
          {
            "duration": 3.257303613,
            "location": "features/Login.feature:24"
          }
        ]
      },
      {
        "name": "PruBuddy sends Response Text \"Yes or No\"",
        "aggregatedDurations": {
          "average": 3.617063877,
          "median": 3.617063877
        },
        "durations": [
          {
            "duration": 3.617063877,
            "location": "features/Login.feature:24"
          }
        ]
      },
      {
        "name": "PruBuddy sends Response Text \"You are entitled to 22 days of leave per annum\"",
        "aggregatedDurations": {
          "average": 3.749994814,
          "median": 3.749994814
        },
        "durations": [
          {
            "duration": 3.749994814,
            "location": "features/Login.feature:24"
          }
        ]
      }
    ]
  },
  {
    "source": "^Elements in Home Page are Validated$",
    "steps": [
      {
        "name": "Elements in Home Page are Validated",
        "aggregatedDurations": {
          "average": 2.854945255,
          "median": 2.854945255
        },
        "durations": [
          {
            "duration": 2.854945255,
            "location": "features/Login.feature:13"
          }
        ]
      }
    ]
  },
  {
    "source": "^User Opens Prutopia Application$",
    "steps": [
      {
        "name": "User Opens Prutopia Application",
        "aggregatedDurations": {
          "average": 0.202541066,
          "median": 0.202541066
        },
        "durations": [
          {
            "duration": 0.202541066,
            "location": "features/Login.feature:5"
          }
        ]
      }
    ]
  },
  {
    "source": "^User is Navigated to Home Page of the Application$",
    "steps": [
      {
        "name": "User is Navigated to Home Page of the Application",
        "aggregatedDurations": {
          "average": 5.436482114,
          "median": 5.436482114
        },
        "durations": [
          {
            "duration": 5.436482114,
            "location": "features/Login.feature:12"
          }
        ]
      }
    ]
  },
  {
    "source": "^User sends Request Text \"(.*?)\"$",
    "steps": [
      {
        "name": "User sends Request Text \"Hi\"",
        "aggregatedDurations": {
          "average": 10.499608179,
          "median": 10.499608179
        },
        "durations": [
          {
            "duration": 10.499608179,
            "location": "features/Login.feature:23"
          }
        ]
      },
      {
        "name": "User sends Request Text \"My Leave\"",
        "aggregatedDurations": {
          "average": 11.579682476,
          "median": 11.579682476
        },
        "durations": [
          {
            "duration": 11.579682476,
            "location": "features/Login.feature:23"
          }
        ]
      },
      {
        "name": "User sends Request Text \"Senior Manager\"",
        "aggregatedDurations": {
          "average": 12.663442556,
          "median": 12.663442556
        },
        "durations": [
          {
            "duration": 12.663442556,
            "location": "features/Login.feature:23"
          }
        ]
      },
      {
        "name": "User sends Request Text \"Yes\"",
        "aggregatedDurations": {
          "average": 13.115125378,
          "median": 13.115125378
        },
        "durations": [
          {
            "duration": 13.115125378,
            "location": "features/Login.feature:23"
          }
        ]
      },
      {
        "name": "User sends Request Text \"2) 10 years or longer\"",
        "aggregatedDurations": {
          "average": 16.088397139,
          "median": 16.088397139
        },
        "durations": [
          {
            "duration": 16.088397139,
            "location": "features/Login.feature:23"
          }
        ]
      },
      {
        "name": "User sends Request Text \"Working hours\"",
        "aggregatedDurations": {
          "average": 16.302926969,
          "median": 16.302926969
        },
        "durations": [
          {
            "duration": 16.302926969,
            "location": "features/Login.feature:23"
          }
        ]
      },
      {
        "name": "User sends Request Text \"1) Head office\"",
        "aggregatedDurations": {
          "average": 17.199028801,
          "median": 17.199028801
        },
        "durations": [
          {
            "duration": 17.199028801,
            "location": "features/Login.feature:23"
          }
        ]
      }
    ]
  }
]